{
  "page_number": 141,
  "page_width": 5312,
  "page_height": 6875,
  "render_dpi": 150,
  "polygon": [
    {
      "x": 181,
      "y": 670
    },
    {
      "x": 2666,
      "y": 824
    },
    {
      "x": 5273,
      "y": 833
    },
    {
      "x": 5288,
      "y": 6001
    },
    {
      "x": 4167,
      "y": 6331
    },
    {
      "x": 3336,
      "y": 6372
    },
    {
      "x": 40,
      "y": 6835
    },
    {
      "x": 40,
      "y": 3438
    }
  ],
  "source_pdf": "/Workspace/Projects/Solanus-Project-Pipeline/step_1/cleaned_pdfs/Volume_3.pdf"
}