{
  "page_number": 6,
  "source_file": "/Workspace/Projects/Solanus-Project-Pipeline/step_1/cleaned_pdfs/Appendix_3.pdf",
  "page_width": 5185,
  "page_height": 6852,
  "render_dpi": 150,
  "num_documents": 1,
  "documents": {
    "doc_1": {
      "document_content": [
        [
          {
            "x": 0,
            "y": 895
          },
          {
            "x": 2602,
            "y": 1092
          },
          {
            "x": 4487,
            "y": 807
          },
          {
            "x": 4571,
            "y": 5455
          },
          {
            "x": 2665,
            "y": 5635
          },
          {
            "x": 2567,
            "y": 6540
          },
          {
            "x": 0,
            "y": 6835
          },
          {
            "x": 0,
            "y": 3438
          }
        ]
      ],
      "header_data": [],
      "commentary": [],
      "possessor_notes": [],
      "other": [],
      "src_content": [
        [
          {
            "x": 0,
            "y": 895
          },
          {
            "x": 2602,
            "y": 1092
          },
          {
            "x": 4487,
            "y": 807
          },
          {
            "x": 4571,
            "y": 5455
          },
          {
            "x": 2665,
            "y": 5635
          },
          {
            "x": 2567,
            "y": 6540
          },
          {
            "x": 0,
            "y": 6835
          },
          {
            "x": 0,
            "y": 3438
          }
        ]
      ]
    }
  }
}