{
  "page_number": 280,
  "page_width": 5312,
  "page_height": 6875,
  "render_dpi": 150,
  "polygon": [
    {
      "x": 31,
      "y": 895
    },
    {
      "x": 2655,
      "y": 874
    },
    {
      "x": 5273,
      "y": 833
    },
    {
      "x": 5312,
      "y": 2806
    },
    {
      "x": 2603,
      "y": 2883
    },
    {
      "x": 1996,
      "y": 2980
    },
    {
      "x": 1242,
      "y": 3057
    },
    {
      "x": 0,
      "y": 3099
    }
  ],
  "source_pdf": "/Workspace/Projects/Solanus-Project-Pipeline/step_1/cleaned_pdfs/Volume_1.pdf"
}