{
  "page_number": 76,
  "page_width": 5312,
  "page_height": 6875,
  "render_dpi": 150,
  "polygon": [
    {
      "x": 58,
      "y": 1073
    },
    {
      "x": 2644,
      "y": 1121
    },
    {
      "x": 5194,
      "y": 1141
    },
    {
      "x": 5262,
      "y": 5843
    },
    {
      "x": 3346,
      "y": 5315
    },
    {
      "x": 1351,
      "y": 5257
    },
    {
      "x": 40,
      "y": 6835
    },
    {
      "x": 40,
      "y": 3438
    }
  ],
  "source_pdf": "/Workspace/Projects/Solanus-Project-Pipeline/step_1/cleaned_pdfs/Volume_2.pdf"
}