{
  "page_number": 250,
  "page_width": 5312,
  "page_height": 6875,
  "render_dpi": 150,
  "polygon": [
    {
      "x": 487,
      "y": 1157
    },
    {
      "x": 2655,
      "y": 874
    },
    {
      "x": 5273,
      "y": 833
    },
    {
      "x": 5288,
      "y": 6001
    },
    {
      "x": 3403,
      "y": 6011
    },
    {
      "x": 3215,
      "y": 5823
    },
    {
      "x": 398,
      "y": 6053
    },
    {
      "x": 414,
      "y": 3440
    }
  ],
  "source_pdf": "/Workspace/Projects/Solanus-Project-Pipeline/step_1/cleaned_pdfs/Volume_2.pdf"
}