{
  "page_number": 250,
  "page_width": 5312,
  "page_height": 6875,
  "render_dpi": 150,
  "polygon": [
    {
      "x": 321,
      "y": 489
    },
    {
      "x": 2659,
      "y": 726
    },
    {
      "x": 5228,
      "y": 684
    },
    {
      "x": 5179,
      "y": 5647
    },
    {
      "x": 3403,
      "y": 6011
    },
    {
      "x": 2813,
      "y": 6338
    },
    {
      "x": 370,
      "y": 6345
    },
    {
      "x": 174,
      "y": 3441
    }
  ],
  "source_pdf": "/Workspace/Projects/Solanus-Project-Pipeline/step_1/cleaned_pdfs/Volume_4.pdf"
}