{
  "page_number": 24,
  "page_width": 5327,
  "page_height": 6833,
  "render_dpi": 150,
  "polygon": [
    {
      "x": 90,
      "y": 548
    },
    {
      "x": 2581,
      "y": 576
    },
    {
      "x": 4815,
      "y": 569
    },
    {
      "x": 4746,
      "y": 5335
    },
    {
      "x": 2692,
      "y": 5502
    },
    {
      "x": 2671,
      "y": 6473
    },
    {
      "x": 111,
      "y": 6383
    },
    {
      "x": 40,
      "y": 3436
    }
  ],
  "source_pdf": "/Workspace/Projects/Solanus-Project-Pipeline/step_1/cleaned_pdfs/Appendix_3.pdf"
}